GTransPY/__init__.py
GTransPY/detection.py
GTransPY/helpers.py
GTransPY/trLang/__init__.py
GTransPY/trLang/helpers.py
GTransPY/types.py
gtranspy-0.0.12.dist-info/LICENSE
gtranspy-0.0.12.dist-info/WHEEL
gtranspy-0.0.12.dist-info/METADATA
gtranspy-0.0.12.dist-info/RECORD
