Metadata-Version: 2.1
Name: gtranspy
Version: 0.0.12
Summary: An API Wrapper for Google translate
Home-page: https://github.com/ALiwoto/GTransPY
License: Unlicense License
Keywords: translate,google translate,translator,google,api
Author: ALiwoto
Author-email: aminnimaj@gmail.com
Requires-Python: >=3.7,<4.0
Classifier: License :: Other/Proprietary License
Classifier: Programming Language :: Python :: 3
Classifier: Programming Language :: Python :: 3.7
Classifier: Programming Language :: Python :: 3.8
Classifier: Programming Language :: Python :: 3.9
Requires-Dist: httpx (>=0.18.2,<0.19.0)
